{
	"id": "4dcdf5d2-7f38-4bc8-b232-0fce537400cf",
	"name": "Automation Workshop 101 #2",
	"values": [
		{
			"key": "host",
			"value": "ec2-13-50-131-189.eu-north-1.compute.amazonaws.com",
			"type": "default",
			"enabled": true
		},
		{
			"key": "bigip_user",
			"value": "bigipuser",
			"type": "default",
			"enabled": true
		},
		{
			"key": "bigip_pass",
			"value": "kZMERAcCIDn8oRgH",
			"type": "secret",
			"enabled": true
		}
	],
	"_postman_variable_scope": "environment",
	"_postman_exported_at": "2023-05-03T20:28:06.688Z",
	"_postman_exported_using": "Postman/10.13.0"
}